README.md
mediaspace_extractor.py
setup.py
mediaspace_extractor.egg-info/PKG-INFO
mediaspace_extractor.egg-info/SOURCES.txt
mediaspace_extractor.egg-info/dependency_links.txt
mediaspace_extractor.egg-info/entry_points.txt
mediaspace_extractor.egg-info/requires.txt
mediaspace_extractor.egg-info/top_level.txt