Metadata-Version: 1.1
Name: mediaspace-extractor
Version: 0.1.0
Summary: Extract video download links from Mediaspace
Home-page: https://github.com/MatthewScholefield/mediaspace-extractor
Author: Matthew D. Scholefield
Author-email: matthew331199@gmail.com
License: UNKNOWN
Keywords: mediaspace extractor
Platform: UNKNOWN
Classifier: Development Status :: 3 - Alpha
Classifier: Intended Audience :: Developers
Classifier: Programming Language :: Python :: 3
Classifier: Programming Language :: Python :: 3.4
Classifier: Programming Language :: Python :: 3.5
Classifier: Programming Language :: Python :: 3.6
